sequent_peak_algorithm/__init__.py
sequent_peak_algorithm/sequent_peak_algorithm.py
sequent_peak_algorithm-0.0.5.dist-info/LICENSE
sequent_peak_algorithm-0.0.5.dist-info/METADATA
sequent_peak_algorithm-0.0.5.dist-info/WHEEL
sequent_peak_algorithm-0.0.5.dist-info/top_level.txt
sequent_peak_algorithm-0.0.5.dist-info/RECORD
